sttt/__init__.py
sttt/__main__.py
sttt/README.md
sttt-1.0.0.dist-info/entry_points.txt
sttt-1.0.0.dist-info/LICENSE.txt
sttt-1.0.0.dist-info/METADATA
sttt-1.0.0.dist-info/WHEEL
sttt-1.0.0.dist-info/RECORD
