Metadata-Version: 2.1
Name: STTT
Version: 1.0.0
Summary: CLI implementation of the game "Super Tic Tac Toe" written in python
Home-page: https://github.com/Zamiul-rashid/Super-Tic-Tac-Toe
License: MIT
Author: Zamiul, Proyas
Author-email: zamiulrashid1@gmail.com
Requires-Python: >=3.10,<4.0
Classifier: License :: OSI Approved :: MIT License
Classifier: Programming Language :: Python :: 3
Classifier: Programming Language :: Python :: 3.10
Classifier: Programming Language :: Python :: 3.11
Classifier: Programming Language :: Python :: 3.12
